{
    "children": null,
    "attachments": null,
    "relations": [
        {
            "id": 24,
            "issue_id": 82,
            "issue_to_id": 72,
            "relation_type": "blocks",
            "delay": null
        },
        {
            "id": 30,
            "issue_id": 82,
            "issue_to_id": 66,
            "relation_type": "blocks",
            "delay": null
        }
    ],
    "changesets": [
        {
            "revision": "897180ace67d688c0d1f0de25dfc0d0af4912efd",
            "user": {
                "id": 3,
                "name": "IR4T4"
            },
            "comments": "general linux: default fs_hompath is set to 'etlwolf' refs #72 refs #82\n& other side effects. We no longer use genuine ET files (cfg/pk3 etc\n...) !!!,\nfixed\na\ncompiler\nwarning\nin\nSys_Dialog()",
            "committed_on": "2012-10-22T08:17:02Z"
        },
        {
            "revision": "58b5e54445fe76b1e7faa4b13652923d75f575c7",
            "user": {
                "id": 3,
                "name": "IR4T4"
            },
            "comments": "general Windows: unique default fs_homepath name 'WolfETL' for Windows\nrefs\n#72\nrefs #82 - see last commit",
            "committed_on": "2012-10-22T08:20:08Z"
        },
        {
            "revision": "aea8505b5ed196c454287a2feac6098f32f0bf2a",
            "user": {
                "id": 3,
                "name": "IR4T4"
            },
            "comments": "general linux: structure rearranged using new mod 'legacy'. tested on\ndebian6 with install in $HOME and default fs_homepath. Added some\nrequired files for a proper ETL start. refs #82",
            "committed_on": "2012-10-23T10:40:09Z"
        },
        {
            "revision": "bf7c5bf33e50400116ae2c59493b15418880ae5b",
            "user": {
                "id": 3,
                "name": "IR4T4"
            },
            "comments": "general linux: missing files for last commit refs #82",
            "committed_on": "2012-10-23T10:48:40Z"
        },
        {
            "revision": "c151957b81d61fe752411680a65f333cdc065672",
            "user": {
                "id": 3,
                "name": "IR4T4"
            },
            "comments": "general linux: start scripts for ET Legacy refs #82",
            "committed_on": "2012-10-23T14:10:21Z"
        },
        {
            "revision": "0b4ec89e89bcce8c8437180b9255ab9855047f47",
            "user": {
                "id": 3,
                "name": "IR4T4"
            },
            "comments": "general: legacy mod is started per default when fs_game isn't set via\nparam refs #72, refs #39, refs #82",
            "committed_on": "2012-10-27T09:06:15Z"
        }
    ],
    "journals": [
        {
            "id": 341,
            "user": {
                "id": 3,
                "name": "IR4T4"
            },
            "notes": "Update: mod path name is 'etl' now",
            "created_on": "2012-10-05T10:48:21Z",
            "details": [
                {
                    "property": "attr",
                    "name": "subject",
                    "old_value": "Create a new mod path for etlmain",
                    "new_value": "Create a new mod path for etl"
                }
            ]
        },
        {
            "id": 342,
            "user": {
                "id": 3,
                "name": "IR4T4"
            },
            "notes": "*New Structure*\n\netl\netlded\n\netmain (backward compability):\n - pak0\n - pak1\n - pak2\n - mp_bin (genuine)\n - ui_mp_x86.dll (ETL)\n - qagame_mp_x86.dll (ETL)\n - cgame_mp_x86.dll (ETL)\n\nlegacy: \n - etl_pak3\n - etl_mp_bin\n - qagame_mp_x86.dll (ETL - listen servers)\n\nImportant notes: \nfs_homepath and fs_basepath have to differ (for windows users as well see documents path) This ensures the install itself won't be messed up with downloaded pk3s later on. \nKeep in mind UI and CG binaries are extracted to fs_homepath/legacy on start.",
            "created_on": "2012-10-05T13:32:19Z",
            "details": []
        },
        {
            "id": 350,
            "user": {
                "id": 3,
                "name": "IR4T4"
            },
            "notes": "",
            "created_on": "2012-10-06T11:12:10Z",
            "details": [
                {
                    "property": "attr",
                    "name": "subject",
                    "old_value": "Create a new mod path for etl",
                    "new_value": "Create a new mod path for 'legacy'"
                }
            ]
        },
        {
            "id": 351,
            "user": {
                "id": 3,
                "name": "IR4T4"
            },
            "notes": "I did run some tests and had slightly to adjust the structure:\r\n\r\n- mod path is 'legacy'\r\n- qagame bin is required for listen servers\r\n",
            "created_on": "2012-10-06T11:29:02Z",
            "details": []
        },
        {
            "id": 400,
            "user": {
                "id": 3,
                "name": "IR4T4"
            },
            "notes": "See http://www.etlegacy.com/projects/etlegacy/wiki/ET_Legacy_path_structure",
            "created_on": "2012-10-22T08:39:57Z",
            "details": [
                {
                    "property": "attr",
                    "name": "status_id",
                    "old_value": "1",
                    "new_value": "2"
                },
                {
                    "property": "attr",
                    "name": "done_ratio",
                    "old_value": "0",
                    "new_value": "50"
                }
            ]
        },
        {
            "id": 402,
            "user": {
                "id": 3,
                "name": "IR4T4"
            },
            "notes": "",
            "created_on": "2012-10-22T08:45:26Z",
            "details": [
                {
                    "property": "attr",
                    "name": "assigned_to_id",
                    "new_value": "3"
                }
            ]
        },
        {
            "id": 403,
            "user": {
                "id": 15,
                "name": "muessli"
            },
            "notes": "Hi IT4T4,\r\nfor new Structure; Typo:\r\n\r\netled should be *etlded*!?\r\n\r\nmfg muessli",
            "created_on": "2012-10-22T11:10:17Z",
            "details": []
        },
        {
            "id": 404,
            "user": {
                "id": 3,
                "name": "IR4T4"
            },
            "notes": "You are right (fixed) ... above wiki link is more up to date.",
            "created_on": "2012-10-22T11:50:05Z",
            "details": []
        },
        {
            "id": 406,
            "user": {
                "id": 3,
                "name": "IR4T4"
            },
            "notes": "CMakeLists.txt adapted to fit requirements.\r\n\r\n{TODO} Windows installer",
            "created_on": "2012-10-23T11:02:06Z",
            "details": [
                {
                    "property": "attr",
                    "name": "done_ratio",
                    "old_value": "50",
                    "new_value": "70"
                }
            ]
        },
        {
            "id": 408,
            "user": {
                "id": 3,
                "name": "IR4T4"
            },
            "notes": "",
            "created_on": "2012-10-25T07:58:16Z",
            "details": [
                {
                    "property": "attr",
                    "name": "status_id",
                    "old_value": "2",
                    "new_value": "4"
                },
                {
                    "property": "attr",
                    "name": "done_ratio",
                    "old_value": "70",
                    "new_value": "90"
                }
            ]
        },
        {
            "id": 411,
            "user": {
                "id": 3,
                "name": "IR4T4"
            },
            "notes": "",
            "created_on": "2012-10-26T09:28:13Z",
            "details": [
                {
                    "property": "attr",
                    "name": "status_id",
                    "old_value": "4",
                    "new_value": "5"
                },
                {
                    "property": "attr",
                    "name": "done_ratio",
                    "old_value": "90",
                    "new_value": "100"
                }
            ]
        }
    ],
    "watchers": [],
    "time_entries": null,
    "id": 82,
    "project": {
        "id": 1,
        "name": "ET: Legacy Development"
    },
    "tracker": {
        "id": 2,
        "name": "Feature"
    },
    "status": {
        "id": 5,
        "name": "Fixed"
    },
    "priority": {
        "id": 5,
        "name": "High"
    },
    "author": {
        "id": 3,
        "name": "IR4T4"
    },
    "assigned_to": {
        "id": 3,
        "name": "IR4T4"
    },
    "category": {
        "id": 12,
        "name": "General"
    },
    "fixed_version": {
        "id": 1,
        "name": "2.70rc1"
    },
    "subject": "Create a new mod path for 'legacy'",
    "description": "Extend the project and installer to create a new mod path 'etlmain'\r\n\r\nWe have a benefit of et:l mod code bins (not used for online gaming see #72)\r\n- ui (see et:l mod server browser)\r\n- cg_game (start et:l listen server beside online configuration of etmain)\r\n\r\netl +set fs_game etlmain\r\n\r\n\r\nNote: we may add additional OS builds (AROS/openBSD?) into mp_bin.pk3 w/o messing up sv_pure ",
    "start_date": "2012-10-03",
    "done_ratio": 100,
    "custom_fields": [
        {
            "id": 1,
            "name": "OS"
        },
        {
            "id": 2,
            "name": "Arch"
        }
    ],
    "created_on": "2012-10-03T14:47:57Z",
    "updated_on": "2012-10-26T09:28:13Z",
    "closed_on": "2012-10-26T09:28:13Z"
}