{
    "children": null,
    "attachments": null,
    "relations": null,
    "changesets": [],
    "journals": [
        {
            "id": 6463,
            "user": {
                "id": 281,
                "name": "thunder"
            },
            "notes": "also assault_rock is 4 missing textures:\r\nground_c07a\r\nground_c09a\r\nhaze_vil_night\r\nhaze2\r\n\r\n*//EDIT_kemon: DONE*",
            "created_on": "2017-02-23T19:22:42Z",
            "details": []
        },
        {
            "id": 6464,
            "user": {
                "id": 281,
                "name": "thunder"
            },
            "notes": "Battery:\r\nseawall_ocean.tga\r\n\r\n!!This might be just a shader created from other textures!!\r\n\r\n*//EDIT_kemon: INVALID - seawall_ocean.tga is only an editorimage and not a real texture*",
            "created_on": "2017-02-23T19:57:53Z",
            "details": []
        },
        {
            "id": 6465,
            "user": {
                "id": 281,
                "name": "thunder"
            },
            "notes": "bunker_sd:\r\n\r\nextwall01_sand\r\nextwall02_sand\r\ngirder01\r\ntinroof01\r\nwirefence01\r\n\r\n*//EDIT_kemon: DONE*",
            "created_on": "2017-02-25T22:28:38Z",
            "details": []
        },
        {
            "id": 6466,
            "user": {
                "id": 281,
                "name": "thunder"
            },
            "notes": "castle_door:\r\n\r\ndoor_m01\r\n\r\n*//EDIT_kemon: DONE*",
            "created_on": "2017-02-26T07:20:24Z",
            "details": []
        },
        {
            "id": 6467,
            "user": {
                "id": 281,
                "name": "thunder"
            },
            "notes": "castle floor\r\n\r\nfloor_c10\r\n\r\n*//EDIT_kemon: DONE*",
            "created_on": "2017-02-26T07:39:48Z",
            "details": []
        },
        {
            "id": 6468,
            "user": {
                "id": 281,
                "name": "thunder"
            },
            "notes": "castle_window\r\n\r\ncashudder_c01\r\n\r\n*//EDIT_kemon: DONE*",
            "created_on": "2017-02-26T07:41:54Z",
            "details": []
        },
        {
            "id": 6469,
            "user": {
                "id": 281,
                "name": "thunder"
            },
            "notes": "textures/castle_wood/cwood_c18\r\ntextures/castle_wood/cwood_mo5c\r\ntextures/castle_wood/cwood_mo5cb\r\n\r\n*//EDIT_kemon: DONE*",
            "created_on": "2017-02-26T07:45:46Z",
            "details": []
        },
        {
            "id": 6470,
            "user": {
                "id": 281,
                "name": "thunder"
            },
            "notes": "textures/chat/book_c03\r\ntextures/chat/carpet_c02\r\ntextures/chat/carpet_c08\r\ntextures/chat/carpet_c10\r\ntextures/chat/carpet_c10trim\r\ntextures/chat/carpet_c11\r\ntextures/chat/carpet_c14trim\r\ntextures/chat/office_c03\r\n\r\n*//EDIT_kemon: DONE*",
            "created_on": "2017-02-26T08:16:02Z",
            "details": []
        },
        {
            "id": 6472,
            "user": {
                "id": 281,
                "name": "thunder"
            },
            "notes": "textures/chat_window/chwindow_c06.tga\r\n\r\ntextures/chat_window/chwindow_c05",
            "created_on": "2017-02-26T16:24:14Z",
            "details": []
        },
        {
            "id": 6473,
            "user": {
                "id": 281,
                "name": "thunder"
            },
            "notes": "textures/chateau/desk_c03\r\ntextures/chateau/fireplace_01\r\ntextures/chateau/floor_c04\r\ntextures/chateau/floor_c05\r\ntextures/chateau/floor_c06\r\ntextures/chateau/stair_c01\r\ntextures/chateau/stair_c03\r\ntextures/chateau/trim_c01\r\ntextures/chateau/trim_c03\r\ntextures/chateau/trim_c08\r\ntextures/chateau/trim_c10\r\ntextures/chateau/trim_c14\r\ntextures/chateau/wood_c06\r\ntextures/chateau/wood_c07\r\ntextures/chateau/wood_c09\r\ntextures/chateau/wood_c20\r\ntextures/chateau/window_c03a\r\ntextures/chateau/window_c01.blend.tga\r\ntextures/chateau/window_c04a.tga\r\ntextures/chateau/window_c02.blend.tga\r\ntextures/chateau/window_c07a.tga\r\ntextures/chateau/window_c05.blend.tga\r\n\r\n\r\n\r\n\r\n",
            "created_on": "2017-02-26T16:31:52Z",
            "details": []
        },
        {
            "id": 6474,
            "user": {
                "id": 281,
                "name": "thunder"
            },
            "notes": "a bunch in decals shader",
            "created_on": "2017-02-26T18:06:13Z",
            "details": []
        },
        {
            "id": 6477,
            "user": {
                "id": 256,
                "name": "keMoN"
            },
            "notes": "",
            "created_on": "2017-02-28T12:08:10Z",
            "details": [
                {
                    "property": "attr",
                    "name": "done_ratio",
                    "old_value": "0",
                    "new_value": "20"
                }
            ]
        },
        {
            "id": 6481,
            "user": {
                "id": 281,
                "name": "thunder"
            },
            "notes": "textures/egypt_door_sd/heavy_door_01",
            "created_on": "2017-02-28T17:01:42Z",
            "details": []
        },
        {
            "id": 6482,
            "user": {
                "id": 281,
                "name": "thunder"
            },
            "notes": "textures/egypt_floor_sd/desertsand_light\r\ntextures/egypt_floor_sd/mudroad01\r\ntextures/egypt_floor_sd/mudroad01_trim\r\ntextures/egypt_floor_sd/desertsand_generic_a\r\ntextures/egypt_floor_sd/siwa_sandygrass\r\n\r\n*//EDIT_kemon: DONE*",
            "created_on": "2017-02-28T18:09:07Z",
            "details": []
        },
        {
            "id": 6483,
            "user": {
                "id": 281,
                "name": "thunder"
            },
            "notes": "none of egypt_rock textures exist it seems",
            "created_on": "2017-02-28T19:16:16Z",
            "details": []
        },
        {
            "id": 6503,
            "user": {
                "id": 256,
                "name": "keMoN"
            },
            "notes": "Being applied in \"this\":https://gitlab.com/etlegacy/etlegacy_additional_textures repository.",
            "created_on": "2017-03-04T11:26:01Z",
            "details": []
        },
        {
            "id": 6523,
            "user": {
                "id": 281,
                "name": "thunder"
            },
            "notes": "textures/rock/dam_m01a",
            "created_on": "2017-03-06T08:13:49Z",
            "details": []
        },
        {
            "id": 6524,
            "user": {
                "id": 281,
                "name": "thunder"
            },
            "notes": "textures/rubble/burn_flr_m01a.tga\r\ntextures/props/ember1a\r\ntextures/rubble/rebar_m01",
            "created_on": "2017-03-06T08:22:16Z",
            "details": []
        },
        {
            "id": 6525,
            "user": {
                "id": 281,
                "name": "thunder"
            },
            "notes": "textures/miltary_trim/basewd_m02",
            "created_on": "2017-03-06T09:34:09Z",
            "details": []
        },
        {
            "id": 6526,
            "user": {
                "id": 281,
                "name": "thunder"
            },
            "notes": "textures/miltary_wall/miltary_m01\r\n\r\n",
            "created_on": "2017-03-06T10:04:18Z",
            "details": []
        },
        {
            "id": 6527,
            "user": {
                "id": 281,
                "name": "thunder"
            },
            "notes": "textures/props/board_cl01\r\ntextures/props/board_cl01m\r\ntextures/props/board_m01\r\ntextures/props/box_t_m02\r\ntextures/props/flag_l_m01\r\ntextures/props/flag_l_m01_tad\r\ntextures/props/flag_l_m01nomove\r\ntextures/props/flags_m1\r\ntextures/props/flags_m1_fac\r\ntextures/props/flags_m1_snow\r\n\r\ntextures/props/freeze_glass  ( here I allready got an image @Kemon)\r\ntextures/props/fwindow1 ( same here, allready got one)\r\ntextures/props/hayd\r\ntextures/props/panel_d04\r\ntextures/props/sign_c01\r\ntextures/props/sign_c05\r\ntextures/props/table\r\ntextures/props/torch_ember\r\ntextures/props/train_m03\r\ntextures/props/train_m04\r\ntextures/props/wine_c01\r\ntextures/props/wine_c02",
            "created_on": "2017-03-06T10:48:46Z",
            "details": [
                {
                    "property": "attachment",
                    "name": "736",
                    "new_value": "freeze_glass.tga"
                },
                {
                    "property": "attachment",
                    "name": "734",
                    "new_value": "fwindow1.tga"
                },
                {
                    "property": "attachment",
                    "name": "735",
                    "new_value": "fwindow1_n.tga"
                },
                {
                    "property": "attachment",
                    "name": "737",
                    "new_value": "fwindow1_s.tga"
                },
                {
                    "property": "attachment",
                    "name": "738",
                    "new_value": "refer.tga"
                }
            ]
        },
        {
            "id": 6528,
            "user": {
                "id": 281,
                "name": "thunder"
            },
            "notes": "textures/props_sd/barrel_m01_rednwhite\r\ntextures/props_sd/s_generator01",
            "created_on": "2017-03-06T13:11:44Z",
            "details": []
        },
        {
            "id": 6530,
            "user": {
                "id": 281,
                "name": "thunder"
            },
            "notes": "textures/metals_sd/metal_ref1",
            "created_on": "2017-03-06T18:34:31Z",
            "details": []
        },
        {
            "id": 6535,
            "user": {
                "id": 281,
                "name": "thunder"
            },
            "notes": "textures/railway_sd/d_cross\r\ntextures/railway_sd/d_label01\r\ntextures/railway_sd/d_label02\r\ntextures/railway_sd/d_skull\r\ntextures/railway_sd/metaltrim_a\r\ntextures/railway_sd/metalwall_a\r\ntextures/railway_sd/metalwall_b\r\ntextures/railway_sd/metalwall_c\r\ntextures/railway_sd/panel_trim001\r\ntextures/railway_sd/panel_001a\r\ntextures/railway_sd/panel_001b\r\ntextures/railway_sd/panel_001c\r\ntextures/railway_sd/panel_001d\r\ntextures/railway_sd/panel_001e\r\ntextures/railway_sd/support001\r\ntextures/railway_sd/support003",
            "created_on": "2017-03-07T17:13:28Z",
            "details": []
        },
        {
            "id": 6536,
            "user": {
                "id": 281,
                "name": "thunder"
            },
            "notes": "textures/siwa_terrain_sd/siwa_skyenv1.tga\r\ntextures/siwa_terrain_sd/siwa_skyenv2.tga",
            "created_on": "2017-03-07T17:22:25Z",
            "details": []
        },
        {
            "id": 6537,
            "user": {
                "id": 281,
                "name": "thunder"
            },
            "notes": "textures/skies/sky_8.tga\r\ntextures/skies/sky_6.tga\r\ntextures/skies/n_blue2.tga\r\ntextures/skies/vil_clouds1.tga\r\ntextures/skies/topclouds.tga\r\n\r\ntextures/sfx/fog_grey1.tga",
            "created_on": "2017-03-07T17:30:15Z",
            "details": []
        },
        {
            "id": 6541,
            "user": {
                "id": 281,
                "name": "thunder"
            },
            "notes": "textures/snow/s_fence_c07\r\ntextures/snow/s_grass_ml03b\r\ntextures/snow/s_door_c10b_s\r\n",
            "created_on": "2017-03-07T20:15:46Z",
            "details": []
        },
        {
            "id": 6542,
            "user": {
                "id": 281,
                "name": "thunder"
            },
            "notes": "textures/xlab_door/xdoor_m01\r\ntextures/xlab_door/xdoor_m01f",
            "created_on": "2017-03-07T20:28:39Z",
            "details": []
        },
        {
            "id": 6573,
            "user": {
                "id": 281,
                "name": "thunder"
            },
            "notes": "textures/temperate_sd/rock_worn_brown_moss",
            "created_on": "2017-03-18T06:43:04Z",
            "details": []
        },
        {
            "id": 6575,
            "user": {
                "id": 281,
                "name": "thunder"
            },
            "notes": "textures/terrain/grass_dm01\r\n",
            "created_on": "2017-03-18T07:55:31Z",
            "details": []
        },
        {
            "id": 6576,
            "user": {
                "id": 281,
                "name": "thunder"
            },
            "notes": "textures/town_props/streetname_c01\r\n\r\n//Note!\r\ntown_props is a great place for some extra stuff later.. there could be more streetnames and small things here",
            "created_on": "2017-03-18T08:26:03Z",
            "details": []
        },
        {
            "id": 6577,
            "user": {
                "id": 281,
                "name": "thunder"
            },
            "notes": "textures/town_wall/store_c01\r\ntextures/town_wall/store_c02\r\ntextures/town_wall/store_c03_a",
            "created_on": "2017-03-18T08:49:45Z",
            "details": []
        },
        {
            "id": 6578,
            "user": {
                "id": 281,
                "name": "thunder"
            },
            "notes": "textures/town_wood/trenchwood\r\ntextures/town_wood/wood_c02\r\ntextures/town_wood/wood_c11\r\n",
            "created_on": "2017-03-18T08:56:58Z",
            "details": []
        },
        {
            "id": 6579,
            "user": {
                "id": 281,
                "name": "thunder"
            },
            "notes": "textures/villa_sd/villawindow_a",
            "created_on": "2017-03-18T09:05:12Z",
            "details": []
        },
        {
            "id": 6580,
            "user": {
                "id": 281,
                "name": "thunder"
            },
            "notes": "textures/village/villwin_c18",
            "created_on": "2017-03-18T09:09:28Z",
            "details": []
        },
        {
            "id": 6581,
            "user": {
                "id": 281,
                "name": "thunder"
            },
            "notes": "textures/wood/wood_m05\r\ntextures/wood/wood_m05a_usat_snow\r\ntextures/wood/wood_m06_usat\r\ntextures/wood/wood_m06b\r\ntextures/wood/wood_m08\r\ntextures/wood/wood_m08_usat\r\ntextures/wood/wood_m09\r\ntextures/wood/wood_m09_usat\r\ntextures/wood/wood_m11\r\ntextures/wood/wood_m12_usat\r\ntextures/wood/wood_m12a",
            "created_on": "2017-03-18T10:00:23Z",
            "details": []
        },
        {
            "id": 6582,
            "user": {
                "id": 281,
                "name": "thunder"
            },
            "notes": "NOTE! could be more! check all shaders to be sure!!!",
            "created_on": "2017-03-18T10:23:02Z",
            "details": []
        },
        {
            "id": 6584,
            "user": {
                "id": 35,
                "name": "Dragonji"
            },
            "notes": "How about just cleaning up these shaders as adding extra textures will make all maps that use them incompatible with vanilla?",
            "created_on": "2017-03-18T12:18:17Z",
            "details": []
        },
        {
            "id": 6586,
            "user": {
                "id": 281,
                "name": "thunder"
            },
            "notes": "no, @Dragonji\r\nnot if they make R2 read from folder scripts2.. \r\nAllready opened a ticket for this",
            "created_on": "2017-03-18T15:09:28Z",
            "details": []
        },
        {
            "id": 6773,
            "user": {
                "id": 256,
                "name": "keMoN"
            },
            "notes": "textures/tree/tree_m02dm\r\ntextures/metal_misc/diamond_c_01b //Note: texture is actually existing in pak0 - investigate\r\ntextures/wood/wood_m12a //Note: shader appears to be a dummy shader for a different texture (wood_m12) and not for an own texture (wood_m12a)\r\ntextures/metal_misc/ametal_m03a\r\ntextures/metal_misc/ametal_m03ns\r\n\r\n",
            "created_on": "2017-06-15T08:35:03Z",
            "details": []
        },
        {
            "id": 7320,
            "user": {
                "id": 256,
                "name": "keMoN"
            },
            "notes": "models/mapobjects/flag/flag_allied\r\nmodels/mapobjects/flag/flag_axis",
            "created_on": "2018-10-29T19:44:10Z",
            "details": []
        }
    ],
    "watchers": [
        {
            "id": 9,
            "name": "Mateos"
        }
    ],
    "time_entries": null,
    "id": 992,
    "project": {
        "id": 1,
        "name": "ET: Legacy Development"
    },
    "tracker": {
        "id": 3,
        "name": "Task"
    },
    "status": {
        "id": 1,
        "name": "New"
    },
    "priority": {
        "id": 4,
        "name": "Normal"
    },
    "author": {
        "id": 256,
        "name": "keMoN"
    },
    "assigned_to": {
        "id": 256,
        "name": "keMoN"
    },
    "category": {
        "id": 12,
        "name": "General"
    },
    "fixed_version": {
        "id": 4,
        "name": "ALL"
    },
    "parent": {
        "id": 218
    },
    "subject": "add missing textures for existing shaders",
    "description": "There are shaders present in pak0 that point to non-existing textures. Include those textures.\r\n\r\ndecals.shader\r\nliquids.shader",
    "start_date": "2017-02-07",
    "done_ratio": 20,
    "custom_fields": [
        {
            "id": 1,
            "name": "OS",
            "value": ""
        },
        {
            "id": 2,
            "name": "Arch",
            "value": ""
        }
    ],
    "created_on": "2017-02-07T16:12:00Z",
    "updated_on": "2018-10-29T19:44:10Z"
}