{
    "children": null,
    "attachments": null,
    "relations": [
        {
            "id": 337,
            "issue_id": 1039,
            "issue_to_id": 973,
            "relation_type": "relates",
            "delay": null
        }
    ],
    "changesets": [],
    "journals": [
        {
            "id": 6757,
            "user": {
                "id": 256,
                "name": "keMoN"
            },
            "notes": "",
            "created_on": "2017-05-30T11:39:53Z",
            "details": [
                {
                    "property": "relation",
                    "name": "relates",
                    "new_value": "973"
                }
            ]
        },
        {
            "id": 6759,
            "user": {
                "id": 256,
                "name": "keMoN"
            },
            "notes": "This is unfortunately a known and persistent bug. From the image you attached it looks like you are trying to play on Jaymod, so the workaround is downloading/extracting the jaymod files manually, until we fix that bug. \r\nYou can find Jaymod \"here\":https://jaymod.clanfu.org/\r\n\r\nThanks for your report.",
            "created_on": "2017-05-30T11:45:18Z",
            "details": []
        },
        {
            "id": 6760,
            "user": {
                "id": 3,
                "name": "IR4T4"
            },
            "notes": "Afaik this issue is already fixed in master.",
            "created_on": "2017-05-30T14:00:34Z",
            "details": []
        },
        {
            "id": 7064,
            "user": {
                "id": 3,
                "name": "IR4T4"
            },
            "notes": "",
            "created_on": "2018-02-05T13:55:15Z",
            "details": [
                {
                    "property": "attr",
                    "name": "status_id",
                    "old_value": "1",
                    "new_value": "5"
                },
                {
                    "property": "attr",
                    "name": "done_ratio",
                    "old_value": "0",
                    "new_value": "100"
                }
            ]
        }
    ],
    "watchers": [],
    "time_entries": null,
    "id": 1039,
    "project": {
        "id": 1,
        "name": "ET: Legacy Development"
    },
    "tracker": {
        "id": 1,
        "name": "Bug"
    },
    "status": {
        "id": 5,
        "name": "Fixed"
    },
    "priority": {
        "id": 4,
        "name": "Normal"
    },
    "author": {
        "id": 683,
        "name": "AdAstrum"
    },
    "category": {
        "id": 12,
        "name": "General"
    },
    "fixed_version": {
        "id": 19,
        "name": "2.76"
    },
    "subject": "Crashing after map selection on Windows 10",
    "description": "Guys, I loved to play this game years ago and was very happy to find out about your project, I downloaded and installed the client today. However I am having an issue. Initially everything seems to work and I am able to retrieve the list of servers. I pick a server but immediately after pressing \"Join the server\" button the game quits with the error (see attached image). Any ideas what might be causing it?\r\n\r\n",
    "start_date": "2017-05-30",
    "done_ratio": 100,
    "custom_fields": [
        {
            "id": 1,
            "name": "OS",
            "value": "Windows"
        },
        {
            "id": 2,
            "name": "Arch",
            "value": ""
        }
    ],
    "created_on": "2017-05-29T23:44:50Z",
    "updated_on": "2018-02-05T13:55:15Z",
    "closed_on": "2018-02-05T13:55:15Z"
}