{
    "children": null,
    "attachments": null,
    "relations": null,
    "changesets": [
        {
            "revision": "afd0454e3c208a7a7f3b560fa5643a5ace029a54",
            "user": {
                "id": 13,
                "name": "RaFaL"
            },
            "comments": "rendererGLES: first attempt to fix opengles, refs #1100\n\nOpengl ES is very limited compared to desktop OpenGL implementation need\nfurther investiagation.",
            "committed_on": "2018-10-05T12:49:21Z"
        },
        {
            "revision": "cc2b85298e575499b0ac9c1181fe9b45ba8ef7ff",
            "user": {
                "id": 13,
                "name": "RaFaL"
            },
            "comments": "rendererGLES: small optimization, use short instead of int for systems with small memory amount to spare, refs #1100",
            "committed_on": "2018-10-06T21:29:28Z"
        },
        {
            "revision": "bfe77d6d14e5028e76307f44fd548b1745171fd2",
            "user": {
                "id": 13,
                "name": "RaFaL"
            },
            "comments": "rendererGLES: use float numbers in plane2[4] since it will be running on OpenGL ES, use GL_RGBA in glTextImage2D and comment unused code, refs #1100",
            "committed_on": "2018-10-06T21:58:16Z"
        },
        {
            "revision": "fe41e0ee46b15bbac69a88ed6b0ac2f548adfa85",
            "user": {
                "id": 13,
                "name": "RaFaL"
            },
            "comments": "rendererGLES: added some OpenGL ES implementation, refs #1100",
            "committed_on": "2018-10-06T22:07:13Z"
        },
        {
            "revision": "0bcdfdac5213b0f16ea7b0f07d47f9a5213eb9a4",
            "user": {
                "id": 13,
                "name": "RaFaL"
            },
            "comments": "rendererGLES: first attempt to fix opengles, refs #1100\n\nOpengl ES is very limited compared to desktop OpenGL implementation need\nfurther investiagation.",
            "committed_on": "2019-06-08T19:13:54Z"
        },
        {
            "revision": "58fd6431865549330acf25931f5f5d2a358db31e",
            "user": {
                "id": 13,
                "name": "RaFaL"
            },
            "comments": "rendererGLES: small optimization, use short instead of int for systems with small memory amount to spare, refs #1100",
            "committed_on": "2019-06-08T19:13:54Z"
        },
        {
            "revision": "b6e003582afed81de3cd95e94e2de29b4a9c813b",
            "user": {
                "id": 13,
                "name": "RaFaL"
            },
            "comments": "rendererGLES: use float numbers in plane2[4] since it will be running on OpenGL ES, use GL_RGBA in glTextImage2D and comment unused code, refs #1100",
            "committed_on": "2019-06-08T19:13:54Z"
        },
        {
            "revision": "5defda2af716221063164794536e6c4090536a2d",
            "user": {
                "id": 13,
                "name": "RaFaL"
            },
            "comments": "rendererGLES: added some OpenGL ES implementation, refs #1100",
            "committed_on": "2019-06-08T19:13:54Z"
        },
        {
            "revision": "ba622cce4aa5a33bba89b361d50fda7451b99c13",
            "user": {
                "id": 13,
                "name": "RaFaL"
            },
            "comments": "rendererGLES: first attempt to fix opengles, refs #1100\n\nOpengl ES is very limited compared to desktop OpenGL implementation need\nfurther investiagation.",
            "committed_on": "2019-06-10T15:39:16Z"
        },
        {
            "revision": "ac30cc7d4047f2fa9f2b81c5dfe6da605316f1fa",
            "user": {
                "id": 13,
                "name": "RaFaL"
            },
            "comments": "rendererGLES: small optimization, use short instead of int for systems with small memory amount to spare, refs #1100",
            "committed_on": "2019-06-10T15:39:16Z"
        },
        {
            "revision": "c063c96b884cde1f482af12e5958791cb0ae2c7b",
            "user": {
                "id": 13,
                "name": "RaFaL"
            },
            "comments": "rendererGLES: use float numbers in plane2[4] since it will be running on OpenGL ES, use GL_RGBA in glTextImage2D and comment unused code, refs #1100",
            "committed_on": "2019-06-10T15:39:16Z"
        },
        {
            "revision": "bf6f9f4512b669820328ab2355b880e15232be57",
            "user": {
                "id": 13,
                "name": "RaFaL"
            },
            "comments": "rendererGLES: added some OpenGL ES implementation, refs #1100",
            "committed_on": "2019-06-10T15:39:16Z"
        },
        {
            "revision": "b7fb324d1d9885fb4ae7c5bd88b1c235a8d80e03",
            "user": {
                "id": 13,
                "name": "RaFaL"
            },
            "comments": "rendererGLES: first attempt to fix opengles, refs #1100\n\nOpengl ES is very limited compared to desktop OpenGL implementation need\nfurther investiagation.",
            "committed_on": "2019-08-17T13:37:23Z"
        },
        {
            "revision": "54adc12e97159dea7ed014b6baeb369c7b9b2943",
            "user": {
                "id": 13,
                "name": "RaFaL"
            },
            "comments": "rendererGLES: small optimization, use short instead of int for systems with small memory amount to spare, refs #1100",
            "committed_on": "2019-08-17T13:37:23Z"
        },
        {
            "revision": "e33ee42de453693dc026274af36f0e8a5610b0a2",
            "user": {
                "id": 13,
                "name": "RaFaL"
            },
            "comments": "rendererGLES: use float numbers in plane2[4] since it will be running on OpenGL ES, use GL_RGBA in glTextImage2D and comment unused code, refs #1100",
            "committed_on": "2019-08-17T13:37:23Z"
        },
        {
            "revision": "cbca20a06dd4e1d38b4afd25d08b59ae0f65e768",
            "user": {
                "id": 13,
                "name": "RaFaL"
            },
            "comments": "rendererGLES: added some OpenGL ES implementation, refs #1100",
            "committed_on": "2019-08-17T13:37:23Z"
        },
        {
            "revision": "e877226c9cb8fb2e3898d3fefcb5984a8e7463e0",
            "user": {
                "id": 13,
                "name": "RaFaL"
            },
            "comments": "rendererGLES: first attempt to fix opengles, refs #1100\n\nOpengl ES is very limited compared to desktop OpenGL implementation need\nfurther investiagation.",
            "committed_on": "2019-08-17T14:34:24Z"
        },
        {
            "revision": "5ee21d203da85916db3292cf977df5883b8c7a73",
            "user": {
                "id": 13,
                "name": "RaFaL"
            },
            "comments": "rendererGLES: small optimization, use short instead of int for systems with small memory amount to spare, refs #1100",
            "committed_on": "2019-08-17T14:34:24Z"
        },
        {
            "revision": "27f37224792b5c80c1d2129e1083811bf696cebf",
            "user": {
                "id": 13,
                "name": "RaFaL"
            },
            "comments": "rendererGLES: use float numbers in plane2[4] since it will be running on OpenGL ES, use GL_RGBA in glTextImage2D and comment unused code, refs #1100",
            "committed_on": "2019-08-17T14:34:24Z"
        },
        {
            "revision": "d04deb47bab14e16cb0fef7366cb3033dadeeac9",
            "user": {
                "id": 13,
                "name": "RaFaL"
            },
            "comments": "rendererGLES: added some OpenGL ES implementation, refs #1100",
            "committed_on": "2019-08-17T14:34:24Z"
        }
    ],
    "journals": [
        {
            "id": 7264,
            "user": {
                "id": 3,
                "name": "IR4T4"
            },
            "notes": "",
            "created_on": "2018-08-15T14:48:55Z",
            "details": [
                {
                    "property": "attr",
                    "name": "fixed_version_id",
                    "old_value": "19",
                    "new_value": "8"
                }
            ]
        },
        {
            "id": 7533,
            "user": {
                "id": 3,
                "name": "IR4T4"
            },
            "notes": "",
            "created_on": "2019-01-06T08:43:29Z",
            "details": [
                {
                    "property": "attr",
                    "name": "assigned_to_id",
                    "new_value": "13"
                },
                {
                    "property": "attr",
                    "name": "fixed_version_id",
                    "old_value": "8",
                    "new_value": "22"
                }
            ]
        },
        {
            "id": 7575,
            "user": {
                "id": 3,
                "name": "IR4T4"
            },
            "notes": "",
            "created_on": "2019-01-17T13:24:32Z",
            "details": [
                {
                    "property": "attr",
                    "name": "fixed_version_id",
                    "old_value": "22",
                    "new_value": "4"
                }
            ]
        }
    ],
    "watchers": [],
    "time_entries": null,
    "id": 1100,
    "project": {
        "id": 1,
        "name": "ET: Legacy Development"
    },
    "tracker": {
        "id": 3,
        "name": "Task"
    },
    "status": {
        "id": 1,
        "name": "New"
    },
    "priority": {
        "id": 4,
        "name": "Normal"
    },
    "author": {
        "id": 13,
        "name": "RaFaL"
    },
    "assigned_to": {
        "id": 13,
        "name": "RaFaL"
    },
    "category": {
        "id": 12,
        "name": "General"
    },
    "fixed_version": {
        "id": 4,
        "name": "ALL"
    },
    "subject": "Fix opengles to work with Android devices",
    "description": "Opengles needs a lot of changes to make it work with Android.\r\n\r\nNote: I'm limited here since making this happen on Win is too much hassle.",
    "start_date": "2018-08-04",
    "done_ratio": 0,
    "custom_fields": [
        {
            "id": 1,
            "name": "OS",
            "value": ""
        },
        {
            "id": 2,
            "name": "Arch",
            "value": ""
        }
    ],
    "created_on": "2018-08-04T16:14:23Z",
    "updated_on": "2019-01-17T13:24:32Z"
}